LICENSE-libjpeg.txt
jpeg_toolbox/__init__.py
jpeg_toolbox/jpeg_extension.cpython-312-x86_64-linux-gnu.so
jpeg_toolbox/jpeg_toolbox.py
jpeg_toolbox/jpeg_toolbox_extension.c
jpeg_toolbox/jpeg-9c-win/Lib/static_x64/jpeg.lib
jpeg_toolbox/libs/libjpeg.so.9
python_jpeg_toolbox-0.1.0.dist-info/LICENSE-libjpeg.txt
python_jpeg_toolbox-0.1.0.dist-info/LICENSE.txt
python_jpeg_toolbox-0.1.0.dist-info/METADATA
python_jpeg_toolbox-0.1.0.dist-info/WHEEL
python_jpeg_toolbox-0.1.0.dist-info/top_level.txt
python_jpeg_toolbox-0.1.0.dist-info/RECORD
