Metadata-Version: 2.2
Name: python-jpeg-toolbox
Version: 0.1.0
Summary: The JPEG Toolbox for Python
Home-page: https://github.com/daniellerch/python-jpeg-toolbox
Author: Daniel Lerch Hostalot
Author-email: dlerch@gmail.com
Classifier: Programming Language :: Python :: 3
Classifier: License :: OSI Approved :: MIT License
Classifier: Operating System :: OS Independent
Requires-Python: >=3.6
License-File: LICENSE-libjpeg.txt
License-File: LICENSE.txt
Requires-Dist: numpy
Dynamic: author
Dynamic: author-email
Dynamic: classifier
Dynamic: description
Dynamic: description-content-type
Dynamic: home-page
Dynamic: requires-dist
Dynamic: requires-python
Dynamic: summary
